cheesyutils/__init__.py
cheesyutils/funcs.py
cheesyutils/discord_bots/__init__.py
cheesyutils/discord_bots/bot.py
cheesyutils/discord_bots/checks.py
cheesyutils/discord_bots/constants.py
cheesyutils/discord_bots/context.py
cheesyutils/discord_bots/converters.py
cheesyutils/discord_bots/database.py
cheesyutils/discord_bots/embed.py
cheesyutils/discord_bots/errors.py
cheesyutils/discord_bots/help_command.py
cheesyutils/discord_bots/paginator.py
cheesyutils/discord_bots/types.py
cheesyutils/discord_bots/utils.py
cheesyutils/discord_bots/cogs/__init__.py
cheesyutils/discord_bots/cogs/meta.py
cheesyutils/structures/__init__.py
cheesyutils/structures/default_lru.py
cheesyutils/structures/write_through_lru.py
cheesyutils-0.3.5.dist-info/LICENSE
cheesyutils-0.3.5.dist-info/METADATA
cheesyutils-0.3.5.dist-info/WHEEL
cheesyutils-0.3.5.dist-info/top_level.txt
cheesyutils-0.3.5.dist-info/RECORD
