Metadata-Version: 2.1
Name: cheesyutils
Version: 0.3.5
Summary: A python package of miscelanious utilities
Home-page: https://github.com/CheesyGamer77/cheesyutils
Author: CheesyGamer77
License: UNKNOWN
Platform: UNKNOWN
Classifier: Programming Language :: Python :: 3
Classifier: License :: OSI Approved :: MIT License
Classifier: Operating System :: OS Independent
Requires-Python: >=3.6
License-File: LICENSE
Requires-Dist: aiohttp (>=3.6.0)
Requires-Dist: aiosqlite (>=0.17.0)
Requires-Dist: discord.py (>=1.7.1)
Requires-Dist: python-dateutil
